function_parser/__init__.py
function_parser/_nbdev.py
function_parser/build_grammars.py
function_parser/fetch_licenses.py
function_parser/language_data.py
function_parser/parser_cli.py
function_parser/process.py
function_parser/process_calls.py
function_parser/utils.py
function_parser/parsers/__init__.py
function_parser/parsers/commentutils.py
function_parser/parsers/go_parser.py
function_parser/parsers/java_parser.py
function_parser/parsers/javascript_parser.py
function_parser/parsers/language_parser.py
function_parser/parsers/php_parser.py
function_parser/parsers/python_parser.py
function_parser/parsers/ruby_parser.py
function_parser-0.0.4.dist-info/LICENSE
function_parser-0.0.4.dist-info/METADATA
function_parser-0.0.4.dist-info/WHEEL
function_parser-0.0.4.dist-info/entry_points.txt
function_parser-0.0.4.dist-info/top_level.txt
function_parser-0.0.4.dist-info/RECORD
