Metadata-Version: 2.1
Name: function-parser
Version: 0.0.4
Summary: This library contains various utils to parse GitHub repositories into function definition and docstring pairs. It is based on tree-sitter to parse code into ASTs and apply heuristics to parse metadata in more details. Currently, it supports 6 languages: Python, Java, Go, Php, Ruby, and Javascript. It also parses function calls and links them with their definitions for Python.
Home-page: https://github.com/ncoop57/function_parser/tree/main/
Author: Nathan Cooper and CodeSearchNet Team
Author-email: nathanallencooper@gmail.com
License: MIT License (MIT)
Keywords: source code parser method function software engineering
Platform: UNKNOWN
Classifier: Development Status :: 3 - Alpha
Classifier: Intended Audience :: Developers
Classifier: License :: OSI Approved :: MIT License
Classifier: Natural Language :: English
Classifier: Programming Language :: Python :: 3.7
Classifier: Programming Language :: Python :: 3.8
Requires-Python: >=3.7
Requires-Dist: docopt
Requires-Dist: dpu-utils
Requires-Dist: elasticsearch
Requires-Dist: gitpython
Requires-Dist: pandas
Requires-Dist: pyhive
Requires-Dist: python-arango
Requires-Dist: requests
Requires-Dist: tqdm
Requires-Dist: tree-sitter (==0.0.5)
